{
  "name": "sysml",
  "word": "identifier",
  "rules": {
    "source_file": {
      "type": "REPEAT",
      "content": {
        "type": "SYMBOL",
        "name": "_statement"
      }
    },
    "_statement": {
      "type": "CHOICE",
      "members": [
        {
          "type": "SYMBOL",
          "name": "package_decl"
        },
        {
          "type": "SYMBOL",
          "name": "part_def"
        },
        {
          "type": "SYMBOL",
          "name": "attribute_decl"
        },
        {
          "type": "SYMBOL",
          "name": "import_decl"
        },
        {
          "type": "SYMBOL",
          "name": "definition"
        }
      ]
    },
    "block": {
      "type": "SEQ",
      "members": [
        {
          "type": "STRING",
          "value": "{"
        },
        {
          "type": "REPEAT",
          "content": {
            "type": "SYMBOL",
            "name": "_statement"
          }
        },
        {
          "type": "STRING",
          "value": "}"
        }
      ]
    },
    "package_decl": {
      "type": "SEQ",
      "members": [
        {
          "type": "STRING",
          "value": "package"
        },
        {
          "type": "FIELD",
          "name": "name",
          "content": {
            "type": "SYMBOL",
            "name": "identifier"
          }
        },
        {
          "type": "CHOICE",
          "members": [
            {
              "type": "SYMBOL",
              "name": "block"
            },
            {
              "type": "BLANK"
            }
          ]
        }
      ]
    },
    "part_def": {
      "type": "SEQ",
      "members": [
        {
          "type": "STRING",
          "value": "part"
        },
        {
          "type": "CHOICE",
          "members": [
            {
              "type": "STRING",
              "value": "def"
            },
            {
              "type": "BLANK"
            }
          ]
        },
        {
          "type": "FIELD",
          "name": "name",
          "content": {
            "type": "SYMBOL",
            "name": "identifier"
          }
        },
        {
          "type": "CHOICE",
          "members": [
            {
              "type": "SYMBOL",
              "name": "typing"
            },
            {
              "type": "BLANK"
            }
          ]
        },
        {
          "type": "CHOICE",
          "members": [
            {
              "type": "SYMBOL",
              "name": "block"
            },
            {
              "type": "BLANK"
            }
          ]
        },
        {
          "type": "CHOICE",
          "members": [
            {
              "type": "STRING",
              "value": ";"
            },
            {
              "type": "BLANK"
            }
          ]
        }
      ]
    },
    "attribute_decl": {
      "type": "SEQ",
      "members": [
        {
          "type": "STRING",
          "value": "attribute"
        },
        {
          "type": "FIELD",
          "name": "name",
          "content": {
            "type": "SYMBOL",
            "name": "identifier"
          }
        },
        {
          "type": "CHOICE",
          "members": [
            {
              "type": "SYMBOL",
              "name": "typing"
            },
            {
              "type": "BLANK"
            }
          ]
        },
        {
          "type": "CHOICE",
          "members": [
            {
              "type": "STRING",
              "value": ";"
            },
            {
              "type": "BLANK"
            }
          ]
        }
      ]
    },
    "import_decl": {
      "type": "SEQ",
      "members": [
        {
          "type": "STRING",
          "value": "import"
        },
        {
          "type": "PATTERN",
          "value": "[^;]+"
        },
        {
          "type": "STRING",
          "value": ";"
        }
      ]
    },
    "definition": {
      "type": "SEQ",
      "members": [
        {
          "type": "CHOICE",
          "members": [
            {
              "type": "STRING",
              "value": "action"
            },
            {
              "type": "STRING",
              "value": "state"
            },
            {
              "type": "STRING",
              "value": "interface"
            },
            {
              "type": "STRING",
              "value": "port"
            },
            {
              "type": "STRING",
              "value": "requirement"
            },
            {
              "type": "STRING",
              "value": "constraint"
            },
            {
              "type": "STRING",
              "value": "enum"
            },
            {
              "type": "STRING",
              "value": "type"
            }
          ]
        },
        {
          "type": "CHOICE",
          "members": [
            {
              "type": "STRING",
              "value": "def"
            },
            {
              "type": "BLANK"
            }
          ]
        },
        {
          "type": "FIELD",
          "name": "name",
          "content": {
            "type": "SYMBOL",
            "name": "identifier"
          }
        },
        {
          "type": "CHOICE",
          "members": [
            {
              "type": "SYMBOL",
              "name": "block"
            },
            {
              "type": "BLANK"
            }
          ]
        },
        {
          "type": "CHOICE",
          "members": [
            {
              "type": "STRING",
              "value": ";"
            },
            {
              "type": "BLANK"
            }
          ]
        }
      ]
    },
    "typing": {
      "type": "SEQ",
      "members": [
        {
          "type": "STRING",
          "value": ":"
        },
        {
          "type": "FIELD",
          "name": "type",
          "content": {
            "type": "SYMBOL",
            "name": "type_ref"
          }
        }
      ]
    },
    "type_ref": {
      "type": "CHOICE",
      "members": [
        {
          "type": "SYMBOL",
          "name": "qualified_name"
        },
        {
          "type": "SYMBOL",
          "name": "identifier"
        }
      ]
    },
    "qualified_name": {
      "type": "SEQ",
      "members": [
        {
          "type": "SYMBOL",
          "name": "identifier"
        },
        {
          "type": "REPEAT1",
          "content": {
            "type": "SEQ",
            "members": [
              {
                "type": "STRING",
                "value": "::"
              },
              {
                "type": "SYMBOL",
                "name": "identifier"
              }
            ]
          }
        }
      ]
    },
    "identifier": {
      "type": "PATTERN",
      "value": "[A-Za-z_][A-Za-z0-9_]*"
    },
    "string": {
      "type": "PATTERN",
      "value": "\"([^\"\\\\]|\\\\.)*\""
    },
    "number": {
      "type": "PATTERN",
      "value": "\\d+(\\.\\d+)?"
    },
    "comment": {
      "type": "TOKEN",
      "content": {
        "type": "CHOICE",
        "members": [
          {
            "type": "SEQ",
            "members": [
              {
                "type": "STRING",
                "value": "//"
              },
              {
                "type": "PATTERN",
                "value": ".*"
              }
            ]
          },
          {
            "type": "PATTERN",
            "value": "\\/\\*[^*]*\\*+([^/*][^*]*\\*+)*\\/"
          }
        ]
      }
    }
  },
  "extras": [
    {
      "type": "PATTERN",
      "value": "\\s"
    },
    {
      "type": "SYMBOL",
      "name": "comment"
    }
  ],
  "conflicts": [],
  "precedences": [],
  "externals": [],
  "inline": [],
  "supertypes": []
}
